inkstone/__init__.py
inkstone/bx.py
inkstone/conv_mtx_idx.py
inkstone/g_pts.py
inkstone/g_pts_1d.py
inkstone/im.py
inkstone/layer.py
inkstone/layer_copy.py
inkstone/max_idx_diff.py
inkstone/mtr.py
inkstone/params.py
inkstone/recipro.py
inkstone/rsp.py
inkstone/shps.py
inkstone/simulator.py
inkstone/sm.py
inkstone/ft/__init__.py
inkstone/ft/ft_1d_sq.py
inkstone/ft/ft_2d_cnst.py
inkstone/ft/ft_2d_disk.py
inkstone/ft/ft_2d_ellip.py
inkstone/ft/ft_2d_para.py
inkstone/ft/ft_2d_poly.py
inkstone/ft/ft_2d_rct.py
inkstone/ft/gibbs.py
inkstone/ft/poly_area.py
inkstone/helpers/__init__.py
inkstone/helpers/pt_in_poly.py
inkstone-0.3.15.dist-info/LICENSE
inkstone-0.3.15.dist-info/METADATA
inkstone-0.3.15.dist-info/WHEEL
inkstone-0.3.15.dist-info/top_level.txt
inkstone-0.3.15.dist-info/RECORD
