Metadata-Version: 2.1
Name: inkstone
Version: 0.3.15
Summary: 3D efficient solver for multi-stacked in-plane periodic structures using rcwa.
Home-page: https://github.com/alexysong/inkstone
Author: Alex Y. Song
Author-email: song.alexy@gmail.com
Keywords: rcwa
Classifier: Programming Language :: Python :: 3
Classifier: Topic :: Scientific/Engineering
Classifier: License :: OSI Approved :: GNU Affero General Public License v3 or later (AGPLv3+)
License-File: LICENSE
Requires-Dist: numpy (>=1.11.3)
Requires-Dist: scipy
